<?xml version="1.0" encoding="UTF-8"?>
<objects serializationModel="Studio.02.02.00">
	<object class="AudioFile" id="{58795180-cdee-4b3b-951e-d04b49d1cbf4}">
		<property name="assetPath">
			<value>Weapon/Handling/pistol-handling3.wav</value>
		</property>
		<property name="frequencyInKHz">
			<value>96</value>
		</property>
		<property name="channelCount">
			<value>2</value>
		</property>
		<property name="length">
			<value>0.39507291666666666</value>
		</property>
		<relationship name="masterAssetFolder">
			<destination>{22decf5e-0a9c-4720-bc2a-7587ae4a6cdc}</destination>
		</relationship>
	</object>
</objects>
